stubilous/__init__.py
stubilous/__main__.py
stubilous/builder.py
stubilous/config.py
stubilous/server.py
stubilous/version.py
stubilous-0.0.8.dist-info/DESCRIPTION.rst
stubilous-0.0.8.dist-info/METADATA
stubilous-0.0.8.dist-info/RECORD
stubilous-0.0.8.dist-info/WHEEL
stubilous-0.0.8.dist-info/metadata.json
stubilous-0.0.8.dist-info/top_level.txt
