Metadata-Version: 2.0
Name: stubilous
Version: 0.0.8
Summary: A plain simple Python http stub server
Home-page: https://github.com/CodersOfTheNight/stubilous
Author: Šarūnas Navickas
Author-email: zaibacu@gmail.com
License: MIT
Platform: UNKNOWN
